setup.cfg
setup.py
ud_toolkit.egg-info/PKG-INFO
ud_toolkit.egg-info/SOURCES.txt
ud_toolkit.egg-info/dependency_links.txt
ud_toolkit.egg-info/requires.txt
ud_toolkit.egg-info/top_level.txt
udtk/__init__.py
udtk/models.py
udtk/udpipe.py
udtk/utils.py