Metadata-Version: 1.0
Name: ud-toolkit
Version: 0.0.1
Summary: NLP toolkit built around UDPipe.
Home-page: http://github.com/eivindbergem/ud-toolkit
Author: Eivind Alexander Bergem
Author-email: eivind.bergem@gmail.com
License: GPL
Platform: UNKNOWN
